plover_repeat/__init__.py
plover_repeat/plover_repeat.py
plover_repeat-0.2.0.dist-info/METADATA
plover_repeat-0.2.0.dist-info/WHEEL
plover_repeat-0.2.0.dist-info/entry_points.txt
plover_repeat-0.2.0.dist-info/top_level.txt
plover_repeat-0.2.0.dist-info/zip-safe
plover_repeat-0.2.0.dist-info/RECORD
