Metadata-Version: 2.4
Name: plover-repeat
Version: 0.2.0
Summary: Repeat previous strokes in Plover
Author-email: Ryan Tagen <ryan.tagen@gmail.com>
License: GPL-3.0-or-later
Project-URL: Homepage, https://github.com/ryan-0816/plover_repeat
Project-URL: Repository, https://github.com/ryan-0816/plover_repeat
Keywords: plover,plover_plugin,stenography
Classifier: Development Status :: 4 - Beta
Classifier: Environment :: Plugins
Classifier: Intended Audience :: End Users/Desktop
Classifier: Operating System :: OS Independent
Classifier: Programming Language :: Python :: 3
Classifier: Programming Language :: Python :: 3.8
Classifier: Programming Language :: Python :: 3.9
Classifier: Programming Language :: Python :: 3.10
Classifier: Programming Language :: Python :: 3.11
Requires-Python: >=3.8
Requires-Dist: plover>=4.0.0.dev10
